LICENSE
README.md
setup.py
Python_Monitoring_Agent.egg-info/PKG-INFO
Python_Monitoring_Agent.egg-info/SOURCES.txt
Python_Monitoring_Agent.egg-info/dependency_links.txt
Python_Monitoring_Agent.egg-info/entry_points.txt
Python_Monitoring_Agent.egg-info/requires.txt
Python_Monitoring_Agent.egg-info/top_level.txt
app/__init__.py
app/config.py
app/cpu.py
app/disks.py
app/docker.py
app/influx_writer.py
app/main.py
app/memory.py
app/metrics.py
app/net_interfaces.py
app/start.py