Metadata-Version: 2.1
Name: Python-Monitoring-Agent
Version: 0.2.1
Summary: Simple, os independent monitoring agent
Home-page: https://github.com/SzymonRysztof/python-monitoring-agent/
Author: Szymon Rysztof
Requires-Python: >=3.6
License-File: LICENSE
